orbis_plugin_scoring_nel_scorer/__init__.py
orbis_plugin_scoring_nel_scorer/conditions.py
orbis_plugin_scoring_nel_scorer/main.py
tests/__init__.py
tests/test_main.py
orbis_plugin_scoring_nel_scorer-2.2.5.dist-info/LICENSE
orbis_plugin_scoring_nel_scorer-2.2.5.dist-info/METADATA
orbis_plugin_scoring_nel_scorer-2.2.5.dist-info/WHEEL
orbis_plugin_scoring_nel_scorer-2.2.5.dist-info/top_level.txt
orbis_plugin_scoring_nel_scorer-2.2.5.dist-info/RECORD
